feature_flags/__init__.py
feature_flags/v1/__init__.py
feature_flags/v1/interfaces/__init__.py
feature_flags/v1/interfaces/istatefulresourcerepository.py
feature_flags/v1/repositories/__init__.py
feature_flags/v1/repositories/basic_feature_repository.py
feature_flags/v1/services/__init__.py
feature_flags/v1/services/feature_flag_service.py
feature_flags/v1/strategies/__init__.py
feature_flags/v1/strategies/using_basic_flat_file.py
feature_flags/v1/utilities/__init__.py
feature_flags/v1/utilities/find_feature_yaml.py
basicfeatureflags-1.0.0.277.dist-info/METADATA
basicfeatureflags-1.0.0.277.dist-info/WHEEL
basicfeatureflags-1.0.0.277.dist-info/top_level.txt
basicfeatureflags-1.0.0.277.dist-info/RECORD
